teqpflsh/libgeos.dylib
teqpflsh/__init__.py
teqpflsh/_teqpflsh_impl.cpython-312-darwin.so
teqpflsh/py.typed
teqpflsh/_teqpflsh_impl.pyi
teqpflsh/libgeos.3.14.0.dylib
teqpflsh-0.0.4.dist-info/RECORD
teqpflsh-0.0.4.dist-info/WHEEL
teqpflsh-0.0.4.dist-info/METADATA
