Metadata-Version: 2.1
Name: teqpflsh
Version: 0.0.4
Summary: Flash calculations with guesses powered by K-D trees
Author-Email: Ian Bell <ian.bell@nist.gov>
Project-URL: Homepage, https://github.com/usnistgov/teqpflsh
Requires-Python: >=3.12
